[
    {
        "id":  1658,
        "company_id":  "1",
        "project_company_id":  "1",
        "name":  "Dariia Shtuka",
        "link":  "https://www.linkedin.com/in/dariia-shtuka-4a5596305/",
        "connections":  null,
        "premium":  "1",
        "linked_login":  "dariashtuka5@hotmail.com",
        "linked_password":  "Duzgyt-gikqi1-xivkyr",
        "email_login":  "dariashtuka5@hotmail.com",
        "email_password":  "cahbin-xuhpev-9mEvtu",
        "passport_link":  null,
        "mobile":  null,
        "comments":  "почта @hotmail.com\r\nлинкедин деактивирован",
        "buy_date":  null,
        "created_date":  "2024-04-17",
        "banned_date":  null,
        "sold_date":  null,
        "agent_id":  null,
        "status_id":  "5",
        "country_id":  null,
        "source_id":  null,
        "placement_id":  "1",
        "user_id":  null,
        "is_approved_manager":  "1",
        "created_at":  "2024-04-22T12:51:26.000000Z",
        "updated_at":  "2024-05-08T08:59:06.000000Z",
        "status":  {
                       "id":  5,
                       "company_id":  "1",
                       "name":  "Problematic",
                       "created_at":  "2020-09-04T13:03:21.000000Z",
                       "updated_at":  "2020-09-04T13:03:21.000000Z"
                   },
        "country":  null,
        "source":  null,
        "agent":  null,
        "user":  null,
        "project_company":  {
                                "id":  1,
                                "company_id":  "1",
                                "name":  "Remote Helpers",
                                "website":  "https://www.rh-s.com/",
                                "short_name":  "rh-s.com",
                                "created_at":  null,
                                "updated_at":  "2024-01-05T06:56:45.000000Z"
                            },
        "placement":  {
                          "id":  1,
                          "company_id":  "1",
                          "name":  "LinkedIn",
                          "category_id":  "2",
                          "created_at":  "2020-10-26T13:09:46.000000Z",
                          "updated_at":  "2024-01-05T07:05:34.000000Z"
                      },
        "documents":  [

                      ],
        "account_changes":  [
                                {
                                    "id":  3569,
                                    "account_id":  "1658",
                                    "user_id":  "7784",
                                    "value":  "Changed Lead Account Status from Free to Problematic",
                                    "created_at":  "2024-05-08T08:59:06.000000Z",
                                    "updated_at":  "2024-05-08T08:59:06.000000Z",
                                    "user":  null
                                },
                                {
                                    "id":  3570,
                                    "account_id":  "1658",
                                    "user_id":  "7784",
                                    "value":  "Removed Employee Штука Дарья Григорьевна",
                                    "created_at":  "2024-05-08T08:59:06.000000Z",
                                    "updated_at":  "2024-05-08T08:59:06.000000Z",
                                    "user":  null
                                },
                                {
                                    "id":  3571,
                                    "account_id":  "1658",
                                    "user_id":  "7784",
                                    "value":  "Added Approved by manager",
                                    "created_at":  "2024-05-08T08:59:06.000000Z",
                                    "updated_at":  "2024-05-08T08:59:06.000000Z",
                                    "user":  null
                                },
                                {
                                    "id":  3572,
                                    "account_id":  "1658",
                                    "user_id":  "7784",
                                    "value":  "Changed Project Company to Remote Helpers",
                                    "created_at":  "2024-05-08T08:59:06.000000Z",
                                    "updated_at":  "2024-05-08T08:59:06.000000Z",
                                    "user":  null
                                },
                                {
                                    "id":  3573,
                                    "account_id":  "1658",
                                    "user_id":  "7784",
                                    "value":  "Added Created Date 17-04-2024",
                                    "created_at":  "2024-05-08T08:59:06.000000Z",
                                    "updated_at":  "2024-05-08T08:59:06.000000Z",
                                    "user":  null
                                }
                            ],
        "country_histories":  [

                              ],
        "manager_histories":  [

                              ],
        "password_histories":  [

                               ],
        "premium_histories":  [

                              ]
    },
    {
        "id":  1659,
        "company_id":  "1",
        "project_company_id":  "1",
        "name":  "Yaroslav Filinchuk",
        "link":  "https://www.linkedin.com/in/yaroslav-filinchuk-696911306/",
        "connections":  null,
        "premium":  "1",
        "linked_login":  "yfilinchuk7@gmail.com",
        "linked_password":  "D97Y2hMu2b",
        "email_login":  "yfilinchuk7@gmail.com",
        "email_password":  "D97Y2hMu2b",
        "passport_link":  null,
        "mobile":  null,
        "comments":  null,
        "buy_date":  null,
        "created_date":  "2024-05-02",
        "banned_date":  null,
        "sold_date":  null,
        "agent_id":  null,
        "status_id":  "3",
        "country_id":  null,
        "source_id":  null,
        "placement_id":  "1",
        "user_id":  "8488",
        "is_approved_manager":  "1",
        "created_at":  "2024-04-29T07:06:51.000000Z",
        "updated_at":  "2025-03-31T09:34:17.000000Z",
        "status":  {
                       "id":  3,
                       "company_id":  "1",
                       "name":  "Free",
                       "created_at":  "2020-09-04T13:03:19.000000Z",
                       "updated_at":  "2020-09-04T13:03:19.000000Z"
                   },
        "country":  null,
        "source":  null,
        "agent":  null,
        "user":  null,
        "project_company":  {
                                "id":  1,
                                "company_id":  "1",
                                "name":  "Remote Helpers",
                                "website":  "https://www.rh-s.com/",
                                "short_name":  "rh-s.com",
                                "created_at":  null,
                                "updated_at":  "2024-01-05T06:56:45.000000Z"
                            },
        "placement":  {
                          "id":  1,
                          "company_id":  "1",
                          "name":  "LinkedIn",
                          "category_id":  "2",
                          "created_at":  "2020-10-26T13:09:46.000000Z",
                          "updated_at":  "2024-01-05T07:05:34.000000Z"
                      },
        "documents":  [
                          {
                              "id":  477,
                              "account_id":  "1659",
                              "expiration_date":  "2025-11-15",
                              "type_id":  "2",
                              "created_at":  "2024-05-02T09:06:34.000000Z",
                              "updated_at":  "2024-05-02T09:06:34.000000Z",
                              "doc_type":  {
                                               "id":  2,
                                               "company_id":  "1",
                                               "name":  "Driver\u0027s license"
                                           },
                              "links":  [
                                            {
                                                "id":  753,
                                                "document_id":  "477",
                                                "url":  "https://drive.google.com/file/d/1yZw2eDFoTe7jepJ5TPN61QgW1o5K5B-Q/view",
                                                "created_at":  "2024-05-02T09:06:34.000000Z",
                                                "updated_at":  "2024-05-02T09:06:34.000000Z"
                                            },
                                            {
                                                "id":  754,
                                                "document_id":  "477",
                                                "url":  "https://drive.google.com/file/d/1yZw2eDFoTe7jepJ5TPN61QgW1o5K5B-Q/view",
                                                "created_at":  "2024-05-02T09:06:34.000000Z",
                                                "updated_at":  "2024-05-02T09:06:34.000000Z"
                                            }
                                        ]
                          }
                      ],
        "account_changes":  [
                                {
                                    "id":  3333,
                                    "account_id":  "1659",
                                    "user_id":  "5010",
                                    "value":  "Added Approved by manager",
                                    "created_at":  "2024-05-02T09:06:09.000000Z",
                                    "updated_at":  "2024-05-02T09:06:09.000000Z",
                                    "user":  null
                                },
                                {
                                    "id":  3334,
                                    "account_id":  "1659",
                                    "user_id":  "5010",
                                    "value":  "Changed Account Pass from slavik2201 to 633gXu3TgC",
                                    "created_at":  "2024-05-02T09:42:24.000000Z",
                                    "updated_at":  "2024-05-02T09:42:24.000000Z",
                                    "user":  null
                                },
                                {
                                    "id":  3335,
                                    "account_id":  "1659",
                                    "user_id":  "5010",
                                    "value":  "Changed Email Password from slavik2201 to 633gXu3TgC",
                                    "created_at":  "2024-05-02T09:42:24.000000Z",
                                    "updated_at":  "2024-05-02T09:42:24.000000Z",
                                    "user":  null
                                },
                                {
                                    "id":  3336,
                                    "account_id":  "1659",
                                    "user_id":  "5010",
                                    "value":  "Changed Project Company to Remote Helpers",
                                    "created_at":  "2024-05-02T09:42:24.000000Z",
                                    "updated_at":  "2024-05-02T09:42:24.000000Z",
                                    "user":  null
                                },
                                {
                                    "id":  3337,
                                    "account_id":  "1659",
                                    "user_id":  "5010",
                                    "value":  "Added Created Date 02-05-2024",
                                    "created_at":  "2024-05-02T09:42:24.000000Z",
                                    "updated_at":  "2024-05-02T09:42:24.000000Z",
                                    "user":  null
                                },
                                {
                                    "id":  3338,
                                    "account_id":  "1659",
                                    "user_id":  "5010",
                                    "value":  "Changed Account Pass from 633gXu3TgC to 44NF2j2cMy",
                                    "created_at":  "2024-05-02T09:44:39.000000Z",
                                    "updated_at":  "2024-05-02T09:44:39.000000Z",
                                    "user":  null
                                },
                                {
                                    "id":  3339,
                                    "account_id":  "1659",
                                    "user_id":  "5010",
                                    "value":  "Changed Email Password from 633gXu3TgC to 44NF2j2cMy",
                                    "created_at":  "2024-05-02T09:44:39.000000Z",
                                    "updated_at":  "2024-05-02T09:44:39.000000Z",
                                    "user":  null
                                },
                                {
                                    "id":  6183,
                                    "account_id":  "1659",
                                    "user_id":  "5010",
                                    "value":  "Changed Lead Account Status from Free to Change Password",
                                    "created_at":  "2025-03-17T07:31:07.000000Z",
                                    "updated_at":  "2025-03-17T07:31:07.000000Z",
                                    "user":  null
                                },
                                {
                                    "id":  6291,
                                    "account_id":  "1659",
                                    "user_id":  "5010",
                                    "value":  "Changed Account Pass from 44NF2j2cMy to D97Y2hMu2b",
                                    "created_at":  "2025-03-31T09:34:17.000000Z",
                                    "updated_at":  "2025-03-31T09:34:17.000000Z",
                                    "user":  null
                                },
                                {
                                    "id":  6292,
                                    "account_id":  "1659",
                                    "user_id":  "5010",
                                    "value":  "Changed Email Password from 44NF2j2cMy to D97Y2hMu2b",
                                    "created_at":  "2025-03-31T09:34:17.000000Z",
                                    "updated_at":  "2025-03-31T09:34:17.000000Z",
                                    "user":  null
                                },
                                {
                                    "id":  6293,
                                    "account_id":  "1659",
                                    "user_id":  "5010",
                                    "value":  "Changed Lead Account Status from Change Password to Free",
                                    "created_at":  "2025-03-31T09:34:17.000000Z",
                                    "updated_at":  "2025-03-31T09:34:17.000000Z",
                                    "user":  null
                                }
                            ],
        "country_histories":  [

                              ],
        "manager_histories":  [

                              ],
        "password_histories":  [
                                   {
                                       "id":  954,
                                       "account_id":  "1659",
                                       "type":  "account",
                                       "old_pass":  "slavik2201",
                                       "change_date":  "2024-05-02T00:00:00.000000Z",
                                       "created_at":  null,
                                       "updated_at":  null
                                   },
                                   {
                                       "id":  955,
                                       "account_id":  "1659",
                                       "type":  "email",
                                       "old_pass":  "slavik2201",
                                       "change_date":  "2024-05-02T00:00:00.000000Z",
                                       "created_at":  null,
                                       "updated_at":  null
                                   },
                                   {
                                       "id":  956,
                                       "account_id":  "1659",
                                       "type":  "account",
                                       "old_pass":  "633gXu3TgC",
                                       "change_date":  "2024-05-02T00:00:00.000000Z",
                                       "created_at":  null,
                                       "updated_at":  null
                                   },
                                   {
                                       "id":  957,
                                       "account_id":  "1659",
                                       "type":  "email",
                                       "old_pass":  "633gXu3TgC",
                                       "change_date":  "2024-05-02T00:00:00.000000Z",
                                       "created_at":  null,
                                       "updated_at":  null
                                   },
                                   {
                                       "id":  1576,
                                       "account_id":  "1659",
                                       "type":  "account",
                                       "old_pass":  "44NF2j2cMy",
                                       "change_date":  "2025-03-31T00:00:00.000000Z",
                                       "created_at":  null,
                                       "updated_at":  null
                                   },
                                   {
                                       "id":  1577,
                                       "account_id":  "1659",
                                       "type":  "email",
                                       "old_pass":  "44NF2j2cMy",
                                       "change_date":  "2025-03-31T00:00:00.000000Z",
                                       "created_at":  null,
                                       "updated_at":  null
                                   }
                               ],
        "premium_histories":  [

                              ]
    },
    {
        "id":  1660,
        "company_id":  "1",
        "project_company_id":  "1",
        "name":  "Oleh Kushnirenko",
        "link":  "https://www.linkedin.com/in/oleh-kushnirenko-187846306/",
        "connections":  null,
        "premium":  "1",
        "linked_login":  "olehkushnirenko034@gmail.com",
        "linked_password":  "M376msXdM8",
        "email_login":  "olehkushnirenko034@gmail.com",
        "email_password":  "M376msXdM8",
        "passport_link":  null,
        "mobile":  null,
        "comments":  null,
        "buy_date":  null,
        "created_date":  "2024-05-02",
        "banned_date":  null,
        "sold_date":  null,
        "agent_id":  null,
        "status_id":  "3",
        "country_id":  null,
        "source_id":  null,
        "placement_id":  "1",
        "user_id":  "8489",
        "is_approved_manager":  "1",
        "created_at":  "2024-04-29T07:15:32.000000Z",
        "updated_at":  "2024-05-02T09:03:24.000000Z",
        "status":  {
                       "id":  3,
                       "company_id":  "1",
                       "name":  "Free",
                       "created_at":  "2020-09-04T13:03:19.000000Z",
                       "updated_at":  "2020-09-04T13:03:19.000000Z"
                   },
        "country":  null,
        "source":  null,
        "agent":  null,
        "user":  null,
        "project_company":  {
                                "id":  1,
                                "company_id":  "1",
                                "name":  "Remote Helpers",
                                "website":  "https://www.rh-s.com/",
                                "short_name":  "rh-s.com",
                                "created_at":  null,
                                "updated_at":  "2024-01-05T06:56:45.000000Z"
                            },
        "placement":  {
                          "id":  1,
                          "company_id":  "1",
                          "name":  "LinkedIn",
                          "category_id":  "2",
                          "created_at":  "2020-10-26T13:09:46.000000Z",
                          "updated_at":  "2024-01-05T07:05:34.000000Z"
                      },
        "documents":  [
                          {
                              "id":  476,
                              "account_id":  "1660",
                              "expiration_date":  "2034-06-21",
                              "type_id":  "1",
                              "created_at":  "2024-05-02T08:58:35.000000Z",
                              "updated_at":  "2024-05-02T08:58:35.000000Z",
                              "doc_type":  {
                                               "id":  1,
                                               "company_id":  "1",
                                               "name":  "Passport"
                                           },
                              "links":  [
                                            {
                                                "id":  752,
                                                "document_id":  "476",
                                                "url":  "https://drive.google.com/file/d/1umpSLKFqQwI0ZpYBAbkgWzJK55PprV5q/view",
                                                "created_at":  "2024-05-02T08:58:35.000000Z",
                                                "updated_at":  "2024-05-02T08:58:35.000000Z"
                                            }
                                        ]
                          }
                      ],
        "account_changes":  [
                                {
                                    "id":  3328,
                                    "account_id":  "1660",
                                    "user_id":  "5010",
                                    "value":  "Added Approved by manager",
                                    "created_at":  "2024-05-02T08:58:00.000000Z",
                                    "updated_at":  "2024-05-02T08:58:00.000000Z",
                                    "user":  null
                                },
                                {
                                    "id":  3329,
                                    "account_id":  "1660",
                                    "user_id":  "5010",
                                    "value":  "Changed Account Pass from Loid_777123 to M376msXdM8",
                                    "created_at":  "2024-05-02T09:03:24.000000Z",
                                    "updated_at":  "2024-05-02T09:03:24.000000Z",
                                    "user":  null
                                },
                                {
                                    "id":  3330,
                                    "account_id":  "1660",
                                    "user_id":  "5010",
                                    "value":  "Changed Email Password from Loid_777123 to M376msXdM8",
                                    "created_at":  "2024-05-02T09:03:24.000000Z",
                                    "updated_at":  "2024-05-02T09:03:24.000000Z",
                                    "user":  null
                                },
                                {
                                    "id":  3331,
                                    "account_id":  "1660",
                                    "user_id":  "5010",
                                    "value":  "Changed Project Company to Remote Helpers",
                                    "created_at":  "2024-05-02T09:03:24.000000Z",
                                    "updated_at":  "2024-05-02T09:03:24.000000Z",
                                    "user":  null
                                },
                                {
                                    "id":  3332,
                                    "account_id":  "1660",
                                    "user_id":  "5010",
                                    "value":  "Added Created Date 02-05-2024",
                                    "created_at":  "2024-05-02T09:03:24.000000Z",
                                    "updated_at":  "2024-05-02T09:03:24.000000Z",
                                    "user":  null
                                }
                            ],
        "country_histories":  [

                              ],
        "manager_histories":  [

                              ],
        "password_histories":  [
                                   {
                                       "id":  952,
                                       "account_id":  "1660",
                                       "type":  "account",
                                       "old_pass":  "Loid_777123",
                                       "change_date":  "2024-05-02T00:00:00.000000Z",
                                       "created_at":  null,
                                       "updated_at":  null
                                   },
                                   {
                                       "id":  953,
                                       "account_id":  "1660",
                                       "type":  "email",
                                       "old_pass":  "Loid_777123",
                                       "change_date":  "2024-05-02T00:00:00.000000Z",
                                       "created_at":  null,
                                       "updated_at":  null
                                   }
                               ],
        "premium_histories":  [

                              ]
    },
    {
        "id":  1661,
        "company_id":  "1",
        "project_company_id":  "1",
        "name":  "Sofiia Pedash",
        "link":  "http://sofiia-pedash-583117307",
        "connections":  null,
        "premium":  "0",
        "linked_login":  "sofiiapedash@gmail.com",
        "linked_password":  "LH9tGg67f9",
        "email_login":  "sofiiapedash@gmail.com",
        "email_password":  "LH9tGg67f9",
        "passport_link":  null,
        "mobile":  null,
        "comments":  null,
        "buy_date":  null,
        "created_date":  "2024-05-02",
        "banned_date":  null,
        "sold_date":  null,
        "agent_id":  null,
        "status_id":  "3",
        "country_id":  null,
        "source_id":  null,
        "placement_id":  "1",
        "user_id":  "8491",
        "is_approved_manager":  "1",
        "created_at":  "2024-04-29T07:20:07.000000Z",
        "updated_at":  "2024-05-02T08:45:09.000000Z",
        "status":  {
                       "id":  3,
                       "company_id":  "1",
                       "name":  "Free",
                       "created_at":  "2020-09-04T13:03:19.000000Z",
                       "updated_at":  "2020-09-04T13:03:19.000000Z"
                   },
        "country":  null,
        "source":  null,
        "agent":  null,
        "user":  null,
        "project_company":  {
                                "id":  1,
                                "company_id":  "1",
                                "name":  "Remote Helpers",
                                "website":  "https://www.rh-s.com/",
                                "short_name":  "rh-s.com",
                                "created_at":  null,
                                "updated_at":  "2024-01-05T06:56:45.000000Z"
                            },
        "placement":  {
                          "id":  1,
                          "company_id":  "1",
                          "name":  "LinkedIn",
                          "category_id":  "2",
                          "created_at":  "2020-10-26T13:09:46.000000Z",
                          "updated_at":  "2024-01-05T07:05:34.000000Z"
                      },
        "documents":  [
                          {
                              "id":  475,
                              "account_id":  "1661",
                              "expiration_date":  "2033-03-23",
                              "type_id":  "4",
                              "created_at":  "2024-05-02T08:46:46.000000Z",
                              "updated_at":  "2024-05-02T08:46:46.000000Z",
                              "doc_type":  {
                                               "id":  4,
                                               "company_id":  "1",
                                               "name":  "ID card"
                                           },
                              "links":  [
                                            {
                                                "id":  750,
                                                "document_id":  "475",
                                                "url":  "https://drive.google.com/file/d/1nR9MUPJHuznNaFlX6Vf0Ml5AsKlxC2qY/view",
                                                "created_at":  "2024-05-02T08:46:46.000000Z",
                                                "updated_at":  "2024-05-02T08:46:46.000000Z"
                                            },
                                            {
                                                "id":  751,
                                                "document_id":  "475",
                                                "url":  "https://drive.google.com/file/d/1x35VH8q3TIDWuv8ZgLeFef6QH5JheNAd/view",
                                                "created_at":  "2024-05-02T08:46:46.000000Z",
                                                "updated_at":  "2024-05-02T08:46:46.000000Z"
                                            }
                                        ]
                          }
                      ],
        "account_changes":  [
                                {
                                    "id":  3321,
                                    "account_id":  "1661",
                                    "user_id":  "5010",
                                    "value":  "Changed Name from pou190678@gmail.com to Sofiia Pedash",
                                    "created_at":  "2024-05-02T08:31:21.000000Z",
                                    "updated_at":  "2024-05-02T08:31:21.000000Z",
                                    "user":  null
                                },
                                {
                                    "id":  3322,
                                    "account_id":  "1661",
                                    "user_id":  "5010",
                                    "value":  "Changed Account Pass from February2005 to LH9tGg67f9",
                                    "created_at":  "2024-05-02T08:31:21.000000Z",
                                    "updated_at":  "2024-05-02T08:31:21.000000Z",
                                    "user":  null
                                },
                                {
                                    "id":  3323,
                                    "account_id":  "1661",
                                    "user_id":  "5010",
                                    "value":  "Changed Email Password from february2005 to LH9tGg67f9",
                                    "created_at":  "2024-05-02T08:31:21.000000Z",
                                    "updated_at":  "2024-05-02T08:31:21.000000Z",
                                    "user":  null
                                },
                                {
                                    "id":  3324,
                                    "account_id":  "1661",
                                    "user_id":  "5010",
                                    "value":  "Added Approved by manager",
                                    "created_at":  "2024-05-02T08:31:21.000000Z",
                                    "updated_at":  "2024-05-02T08:31:21.000000Z",
                                    "user":  null
                                },
                                {
                                    "id":  3325,
                                    "account_id":  "1661",
                                    "user_id":  "5010",
                                    "value":  "Changed Project Company to Remote Helpers",
                                    "created_at":  "2024-05-02T08:31:21.000000Z",
                                    "updated_at":  "2024-05-02T08:31:21.000000Z",
                                    "user":  null
                                },
                                {
                                    "id":  3326,
                                    "account_id":  "1661",
                                    "user_id":  "5010",
                                    "value":  "Added Created Date 02-05-2024",
                                    "created_at":  "2024-05-02T08:31:21.000000Z",
                                    "updated_at":  "2024-05-02T08:31:21.000000Z",
                                    "user":  null
                                },
                                {
                                    "id":  3327,
                                    "account_id":  "1661",
                                    "user_id":  "5010",
                                    "value":  "Removed Premium",
                                    "created_at":  "2024-05-02T08:45:09.000000Z",
                                    "updated_at":  "2024-05-02T08:45:09.000000Z",
                                    "user":  null
                                }
                            ],
        "country_histories":  [

                              ],
        "manager_histories":  [

                              ],
        "password_histories":  [
                                   {
                                       "id":  950,
                                       "account_id":  "1661",
                                       "type":  "account",
                                       "old_pass":  "February2005",
                                       "change_date":  "2024-05-02T00:00:00.000000Z",
                                       "created_at":  null,
                                       "updated_at":  null
                                   },
                                   {
                                       "id":  951,
                                       "account_id":  "1661",
                                       "type":  "email",
                                       "old_pass":  "february2005",
                                       "change_date":  "2024-05-02T00:00:00.000000Z",
                                       "created_at":  null,
                                       "updated_at":  null
                                   }
                               ],
        "premium_histories":  [

                              ]
    },
    {
        "id":  1662,
        "company_id":  "1",
        "project_company_id":  null,
        "name":  "Oleksandr Dovhanenko",
        "link":  "https://www.linkedin.com/in/oleksandr-dovhanenko/",
        "connections":  null,
        "premium":  "1",
        "linked_login":  "oleksandrremote@gmail.com",
        "linked_password":  "ytyfljwdtnjd1996",
        "email_login":  "oleksandrremote@gmail.com",
        "email_password":  "ytyfljwdtnjd1996",
        "passport_link":  null,
        "mobile":  null,
        "comments":  null,
        "buy_date":  null,
        "created_date":  null,
        "banned_date":  null,
        "sold_date":  null,
        "agent_id":  null,
        "status_id":  "3",
        "country_id":  null,
        "source_id":  null,
        "placement_id":  "1",
        "user_id":  "8490",
        "is_approved_manager":  "1",
        "created_at":  "2024-04-29T08:13:18.000000Z",
        "updated_at":  "2024-05-02T09:45:29.000000Z",
        "status":  {
                       "id":  3,
                       "company_id":  "1",
                       "name":  "Free",
                       "created_at":  "2020-09-04T13:03:19.000000Z",
                       "updated_at":  "2020-09-04T13:03:19.000000Z"
                   },
        "country":  null,
        "source":  null,
        "agent":  null,
        "user":  null,
        "project_company":  null,
        "placement":  {
                          "id":  1,
                          "company_id":  "1",
                          "name":  "LinkedIn",
                          "category_id":  "2",
                          "created_at":  "2020-10-26T13:09:46.000000Z",
                          "updated_at":  "2024-01-05T07:05:34.000000Z"
                      },
        "documents":  [
                          {
                              "id":  478,
                              "account_id":  "1662",
                              "expiration_date":  "2047-03-15",
                              "type_id":  "2",
                              "created_at":  "2024-05-02T09:46:01.000000Z",
                              "updated_at":  "2024-05-02T09:46:01.000000Z",
                              "doc_type":  {
                                               "id":  2,
                                               "company_id":  "1",
                                               "name":  "Driver\u0027s license"
                                           },
                              "links":  [
                                            {
                                                "id":  755,
                                                "document_id":  "478",
                                                "url":  "https://drive.google.com/file/d/15dIqe6gs8KL9AW78Oq7V5y7pnI_cuSEK/view",
                                                "created_at":  "2024-05-02T09:46:01.000000Z",
                                                "updated_at":  "2024-05-02T09:46:01.000000Z"
                                            },
                                            {
                                                "id":  756,
                                                "document_id":  "478",
                                                "url":  "https://drive.google.com/file/d/15dIqe6gs8KL9AW78Oq7V5y7pnI_cuSEK/view",
                                                "created_at":  "2024-05-02T09:46:01.000000Z",
                                                "updated_at":  "2024-05-02T09:46:01.000000Z"
                                            }
                                        ]
                          }
                      ],
        "account_changes":  [
                                {
                                    "id":  3340,
                                    "account_id":  "1662",
                                    "user_id":  "5010",
                                    "value":  "Added Approved by manager",
                                    "created_at":  "2024-05-02T09:45:29.000000Z",
                                    "updated_at":  "2024-05-02T09:45:29.000000Z",
                                    "user":  null
                                }
                            ],
        "country_histories":  [

                              ],
        "manager_histories":  [

                              ],
        "password_histories":  [

                               ],
        "premium_histories":  [

                              ]
    },
    {
        "id":  1663,
        "company_id":  "1",
        "project_company_id":  "1",
        "name":  "Alina Polishchuk",
        "link":  "https://www.linkedin.com/in/polishchukalina/",
        "connections":  "0",
        "premium":  "1",
        "linked_login":  "polishchuk.alina.valeriivna@gmail.com",
        "linked_password":  "tYU75d3Tf9",
        "email_login":  "polishchuk.alina.valeriivna@gmail.com",
        "email_password":  "tYU75d3Tf9",
        "passport_link":  null,
        "mobile":  null,
        "comments":  "нет документов\r\nвозможен рекавери alinaandnusha@gmail.com",
        "buy_date":  null,
        "created_date":  "2024-05-07",
        "banned_date":  null,
        "sold_date":  null,
        "agent_id":  null,
        "status_id":  "3",
        "country_id":  null,
        "source_id":  null,
        "placement_id":  "1",
        "user_id":  "8500",
        "is_approved_manager":  "1",
        "created_at":  "2024-05-07T06:30:57.000000Z",
        "updated_at":  "2024-05-08T09:39:36.000000Z",
        "status":  {
                       "id":  3,
                       "company_id":  "1",
                       "name":  "Free",
                       "created_at":  "2020-09-04T13:03:19.000000Z",
                       "updated_at":  "2020-09-04T13:03:19.000000Z"
                   },
        "country":  null,
        "source":  null,
        "agent":  null,
        "user":  null,
        "project_company":  {
                                "id":  1,
                                "company_id":  "1",
                                "name":  "Remote Helpers",
                                "website":  "https://www.rh-s.com/",
                                "short_name":  "rh-s.com",
                                "created_at":  null,
                                "updated_at":  "2024-01-05T06:56:45.000000Z"
                            },
        "placement":  {
                          "id":  1,
                          "company_id":  "1",
                          "name":  "LinkedIn",
                          "category_id":  "2",
                          "created_at":  "2020-10-26T13:09:46.000000Z",
                          "updated_at":  "2024-01-05T07:05:34.000000Z"
                      },
        "documents":  [

                      ],
        "account_changes":  [
                                {
                                    "id":  3582,
                                    "account_id":  "1663",
                                    "user_id":  "7784",
                                    "value":  "Changed Email Password from Alinusya1510 to tYU75d3Tf9",
                                    "created_at":  "2024-05-08T09:38:00.000000Z",
                                    "updated_at":  "2024-05-08T09:38:00.000000Z",
                                    "user":  null
                                },
                                {
                                    "id":  3583,
                                    "account_id":  "1663",
                                    "user_id":  "7784",
                                    "value":  "Added Approved by manager",
                                    "created_at":  "2024-05-08T09:38:00.000000Z",
                                    "updated_at":  "2024-05-08T09:38:00.000000Z",
                                    "user":  null
                                },
                                {
                                    "id":  3584,
                                    "account_id":  "1663",
                                    "user_id":  "7784",
                                    "value":  "Changed Project Company to Remote Helpers",
                                    "created_at":  "2024-05-08T09:38:00.000000Z",
                                    "updated_at":  "2024-05-08T09:38:00.000000Z",
                                    "user":  null
                                },
                                {
                                    "id":  3585,
                                    "account_id":  "1663",
                                    "user_id":  "7784",
                                    "value":  "Added Created Date 07-05-2024",
                                    "created_at":  "2024-05-08T09:38:00.000000Z",
                                    "updated_at":  "2024-05-08T09:38:00.000000Z",
                                    "user":  null
                                },
                                {
                                    "id":  3586,
                                    "account_id":  "1663",
                                    "user_id":  "7784",
                                    "value":  "Changed Account Pass from Linkedin555555 to tYU75d3Tf9",
                                    "created_at":  "2024-05-08T09:39:36.000000Z",
                                    "updated_at":  "2024-05-08T09:39:36.000000Z",
                                    "user":  null
                                },
                                {
                                    "id":  3587,
                                    "account_id":  "1663",
                                    "user_id":  "7784",
                                    "value":  "Changed Account Pass from Linkedin555555 to tYU75d3Tf9",
                                    "created_at":  "2024-05-08T09:39:36.000000Z",
                                    "updated_at":  "2024-05-08T09:39:36.000000Z",
                                    "user":  null
                                }
                            ],
        "country_histories":  [

                              ],
        "manager_histories":  [

                              ],
        "password_histories":  [
                                   {
                                       "id":  962,
                                       "account_id":  "1663",
                                       "type":  "email",
                                       "old_pass":  "Alinusya1510",
                                       "change_date":  "2024-05-08T00:00:00.000000Z",
                                       "created_at":  null,
                                       "updated_at":  null
                                   },
                                   {
                                       "id":  963,
                                       "account_id":  "1663",
                                       "type":  "account",
                                       "old_pass":  "Linkedin555555",
                                       "change_date":  "2024-05-08T00:00:00.000000Z",
                                       "created_at":  null,
                                       "updated_at":  null
                                   }
                               ],
        "premium_histories":  [

                              ]
    },
    {
        "id":  1665,
        "company_id":  "1",
        "project_company_id":  "1",
        "name":  "Alina Lychana",
        "link":  "https://www.linkedin.com/in/alinalychana/",
        "connections":  null,
        "premium":  "1",
        "linked_login":  "lychanaalina@gmail.com",
        "linked_password":  "Alina_2002",
        "email_login":  "lychanaalina@gmail.com",
        "email_password":  "Alina_2002",
        "passport_link":  null,
        "mobile":  null,
        "comments":  null,
        "buy_date":  null,
        "created_date":  null,
        "banned_date":  null,
        "sold_date":  null,
        "agent_id":  null,
        "status_id":  "3",
        "country_id":  null,
        "source_id":  null,
        "placement_id":  "1",
        "user_id":  "8515",
        "is_approved_manager":  "0",
        "created_at":  "2024-05-13T06:13:41.000000Z",
        "updated_at":  "2024-11-14T14:15:32.000000Z",
        "status":  {
                       "id":  3,
                       "company_id":  "1",
                       "name":  "Free",
                       "created_at":  "2020-09-04T13:03:19.000000Z",
                       "updated_at":  "2020-09-04T13:03:19.000000Z"
                   },
        "country":  null,
        "source":  null,
        "agent":  null,
        "user":  null,
        "project_company":  {
                                "id":  1,
                                "company_id":  "1",
                                "name":  "Remote Helpers",
                                "website":  "https://www.rh-s.com/",
                                "short_name":  "rh-s.com",
                                "created_at":  null,
                                "updated_at":  "2024-01-05T06:56:45.000000Z"
                            },
        "placement":  {
                          "id":  1,
                          "company_id":  "1",
                          "name":  "LinkedIn",
                          "category_id":  "2",
                          "created_at":  "2020-10-26T13:09:46.000000Z",
                          "updated_at":  "2024-01-05T07:05:34.000000Z"
                      },
        "documents":  [

                      ],
        "account_changes":  [
                                {
                                    "id":  5246,
                                    "account_id":  "1665",
                                    "user_id":  "8547",
                                    "value":  "Added LG Manager Дума Виктория Андреевна",
                                    "created_at":  "2024-11-14T14:08:13.000000Z",
                                    "updated_at":  "2024-11-14T14:08:13.000000Z",
                                    "user":  null
                                },
                                {
                                    "id":  5248,
                                    "account_id":  "1665",
                                    "user_id":  "8547",
                                    "value":  "Changed Lead Account Status from Free to LG",
                                    "created_at":  "2024-11-14T14:08:48.000000Z",
                                    "updated_at":  "2024-11-14T14:08:48.000000Z",
                                    "user":  null
                                },
                                {
                                    "id":  5249,
                                    "account_id":  "1665",
                                    "user_id":  "8547",
                                    "value":  "Changed Lead Account Country to France",
                                    "created_at":  "2024-11-14T14:09:18.000000Z",
                                    "updated_at":  "2024-11-14T14:09:18.000000Z",
                                    "user":  null
                                },
                                {
                                    "id":  5250,
                                    "account_id":  "1665",
                                    "user_id":  "8547",
                                    "value":  "Changed Project Company to Remote Helpers",
                                    "created_at":  "2024-11-14T14:09:24.000000Z",
                                    "updated_at":  "2024-11-14T14:09:24.000000Z",
                                    "user":  null
                                },
                                {
                                    "id":  5251,
                                    "account_id":  "1665",
                                    "user_id":  "8547",
                                    "value":  "Removed LG Manager Дума Виктория Андреевна",
                                    "created_at":  "2024-11-14T14:15:05.000000Z",
                                    "updated_at":  "2024-11-14T14:15:05.000000Z",
                                    "user":  null
                                },
                                {
                                    "id":  5252,
                                    "account_id":  "1665",
                                    "user_id":  "8547",
                                    "value":  "Removed Lead Account Country France",
                                    "created_at":  "2024-11-14T14:15:28.000000Z",
                                    "updated_at":  "2024-11-14T14:15:28.000000Z",
                                    "user":  null
                                },
                                {
                                    "id":  5253,
                                    "account_id":  "1665",
                                    "user_id":  "8547",
                                    "value":  "Changed Lead Account Status from LG to Free",
                                    "created_at":  "2024-11-14T14:15:32.000000Z",
                                    "updated_at":  "2024-11-14T14:15:32.000000Z",
                                    "user":  null
                                }
                            ],
        "country_histories":  [
                                  {
                                      "id":  556,
                                      "account_id":  "1665",
                                      "country_id":  "73",
                                      "start_date":  "2024-11-14T00:00:00.000000Z",
                                      "end_date":  "2024-11-14T00:00:00.000000Z",
                                      "created_at":  "2024-11-14T14:09:18.000000Z",
                                      "updated_at":  "2024-11-14T14:15:28.000000Z",
                                      "country":  {
                                                      "id":  73,
                                                      "name":  "France",
                                                      "iso":  "FR",
                                                      "iso3":  "FR",
                                                      "iso_numeric":  "0",
                                                      "nicename":  "",
                                                      "numcode":  null,
                                                      "phonecode":  "0"
                                                  }
                                  }
                              ],
        "manager_histories":  [
                                  {
                                      "id":  518,
                                      "account_id":  "1665",
                                      "agent_id":  "1",
                                      "project_company_id":  "1",
                                      "start_date":  "2024-11-14T00:00:00.000000Z",
                                      "end_date":  "2024-11-14T00:00:00.000000Z",
                                      "created_at":  null,
                                      "updated_at":  null,
                                      "agent":  {
                                                    "id":  1,
                                                    "company_id":  "1",
                                                    "user_id":  "2",
                                                    "status":  "enabled",
                                                    "added_by":  null,
                                                    "last_updated_by":  null,
                                                    "user":  {
                                                                 "id":  2,
                                                                 "company_id":  "1",
                                                                 "name":  "Niko Kar",
                                                                 "email":  "niko@rh-s.com",
                                                                 "image":  "174152dedefe669b5391c8bc063f2f02.jpg",
                                                                 "mobile":  "380997101033",
                                                                 "gender":  "male",
                                                                 "locale":  "en",
                                                                 "status":  "active",
                                                                 "login":  "enable",
                                                                 "onesignal_player_id":  null,
                                                                 "created_at":  "2020-06-25T20:46:02+00:00",
                                                                 "updated_at":  "2023-10-09T10:21:56+00:00",
                                                                 "super_admin":  "0",
                                                                 "email_verification_code":  null,
                                                                 "social_token":  null,
                                                                 "email_notifications":  "1",
                                                                 "two_factor_recovery_codes":  null,
                                                                 "two_factor_confirmed":  "0",
                                                                 "two_factor_email_confirmed":  "0",
                                                                 "salutation":  null,
                                                                 "dark_theme":  "0",
                                                                 "rtl":  "0",
                                                                 "two_fa_verify_via":  null,
                                                                 "two_factor_code":  null,
                                                                 "two_factor_expires_at":  null,
                                                                 "admin_approval":  "1",
                                                                 "permission_sync":  "1",
                                                                 "google_calendar_status":  "1",
                                                                 "country_id":  null,
                                                                 "authorize_id":  null,
                                                                 "authorize_payment_id":  null,
                                                                 "card_brand":  null,
                                                                 "card_last_four":  null,
                                                                 "last_login":  null,
                                                                 "image_url":  "https://crm-s.com/user-uploads/avatar/174152dedefe669b5391c8bc063f2f02.jpg",
                                                                 "modules":  [
                                                                                 "clients",
                                                                                 "employees",
                                                                                 "projects",
                                                                                 "attendance",
                                                                                 "tasks",
                                                                                 "estimates",
                                                                                 "invoices",
                                                                                 "payments",
                                                                                 "timelogs",
                                                                                 "tickets",
                                                                                 "events",
                                                                                 "messages",
                                                                                 "notices",
                                                                                 "leaves",
                                                                                 "leads",
                                                                                 "holidays",
                                                                                 "products",
                                                                                 "expenses",
                                                                                 "contracts",
                                                                                 "reports",
                                                                                 "leadAccount",
                                                                                 "leadAgent",
                                                                                 "leadReports",
                                                                                 "leadActivity",
                                                                                 "hr",
                                                                                 "salesAnalytic",
                                                                                 "hrReports",
                                                                                 "hrBonus",
                                                                                 "accounting",
                                                                                 "changeRole",
                                                                                 "translation",
                                                                                 "leadBonus",
                                                                                 "salesBonus",
                                                                                 "financeEmployees",
                                                                                 "employeesVideoEditing",
                                                                                 "employeesCorrespondence",
                                                                                 "hrCorrespondence",
                                                                                 "exchangeRate",
                                                                                 "smmEmployees",
                                                                                 "contentEmployees",
                                                                                 "copywriterEmployees",
                                                                                 "artistEmployees",
                                                                                 "employeeAnalytics",
                                                                                 "employeeDashboard",
                                                                                 "presales",
                                                                                 "communications",
                                                                                 "ticket support",
                                                                                 "library",
                                                                                 "sms_template",
                                                                                 "send_sms"
                                                                             ]
                                                             }
                                                },
                                      "project_company":  {
                                                              "id":  1,
                                                              "company_id":  "1",
                                                              "name":  "Remote Helpers",
                                                              "website":  "https://www.rh-s.com/",
                                                              "short_name":  "rh-s.com",
                                                              "created_at":  null,
                                                              "updated_at":  "2024-01-05T06:56:45.000000Z"
                                                          }
                                  }
                              ],
        "password_histories":  [

                               ],
        "premium_histories":  [

                              ]
    },
    {
        "id":  1666,
        "company_id":  "1",
        "project_company_id":  "1",
        "name":  "Дарина Красножон",
        "link":  "https://www.linkedin.com/company/technology-\u0026-strategy-t\u0026s-/",
        "connections":  "9",
        "premium":  "1",
        "linked_login":  "krasnozhondaryna11@gmail.com",
        "linked_password":  "K2T67u8tjE",
        "email_login":  "krasnozhondaryna11@gmail.com",
        "email_password":  "K2T67u8tjE",
        "passport_link":  null,
        "mobile":  null,
        "comments":  null,
        "buy_date":  null,
        "created_date":  "2024-08-30",
        "banned_date":  null,
        "sold_date":  null,
        "agent_id":  null,
        "status_id":  "3",
        "country_id":  null,
        "source_id":  null,
        "placement_id":  "1",
        "user_id":  "8511",
        "is_approved_manager":  "1",
        "created_at":  "2024-05-13T06:18:28.000000Z",
        "updated_at":  "2025-01-15T13:09:01.000000Z",
        "status":  {
                       "id":  3,
                       "company_id":  "1",
                       "name":  "Free",
                       "created_at":  "2020-09-04T13:03:19.000000Z",
                       "updated_at":  "2020-09-04T13:03:19.000000Z"
                   },
        "country":  null,
        "source":  null,
        "agent":  null,
        "user":  {
                     "id":  8511,
                     "company_id":  "1",
                     "name":  "Красножон Дарина Владимировна",
                     "email":  "azzaz632azzaz@gmail.com",
                     "image":  "8b572ffb48907f21d669f77c5463275a.jpg",
                     "mobile":  "380986615125",
                     "gender":  "female",
                     "locale":  "en",
                     "status":  "active",
                     "login":  "enable",
                     "onesignal_player_id":  null,
                     "created_at":  "2024-05-12T18:21:05+00:00",
                     "updated_at":  "2024-08-19T16:08:36+00:00",
                     "super_admin":  "0",
                     "email_verification_code":  null,
                     "social_token":  null,
                     "email_notifications":  "1",
                     "two_factor_recovery_codes":  null,
                     "two_factor_confirmed":  "0",
                     "two_factor_email_confirmed":  "0",
                     "salutation":  null,
                     "dark_theme":  "0",
                     "rtl":  "0",
                     "two_fa_verify_via":  null,
                     "two_factor_code":  null,
                     "two_factor_expires_at":  null,
                     "admin_approval":  "1",
                     "permission_sync":  "1",
                     "google_calendar_status":  "1",
                     "country_id":  null,
                     "authorize_id":  null,
                     "authorize_payment_id":  null,
                     "card_brand":  null,
                     "card_last_four":  null,
                     "last_login":  null,
                     "image_url":  "https://crm-s.com/user-uploads/avatar/8b572ffb48907f21d669f77c5463275a.jpg",
                     "modules":  [
                                     "clients",
                                     "employees",
                                     "projects",
                                     "attendance",
                                     "tasks",
                                     "estimates",
                                     "invoices",
                                     "payments",
                                     "timelogs",
                                     "tickets",
                                     "events",
                                     "messages",
                                     "notices",
                                     "leaves",
                                     "leads",
                                     "holidays",
                                     "products",
                                     "expenses",
                                     "contracts",
                                     "reports",
                                     "leadAccount",
                                     "leadAgent",
                                     "leadReports",
                                     "leadActivity",
                                     "hr",
                                     "salesAnalytic",
                                     "hrReports",
                                     "hrBonus",
                                     "accounting",
                                     "changeRole",
                                     "translation",
                                     "leadBonus",
                                     "salesBonus",
                                     "financeEmployees",
                                     "employeesVideoEditing",
                                     "employeesCorrespondence",
                                     "hrCorrespondence",
                                     "exchangeRate",
                                     "smmEmployees",
                                     "contentEmployees",
                                     "copywriterEmployees",
                                     "artistEmployees",
                                     "employeeAnalytics",
                                     "employeeDashboard",
                                     "presales",
                                     "communications",
                                     "ticket support",
                                     "library",
                                     "sms_template",
                                     "send_sms"
                                 ]
                 },
        "project_company":  {
                                "id":  1,
                                "company_id":  "1",
                                "name":  "Remote Helpers",
                                "website":  "https://www.rh-s.com/",
                                "short_name":  "rh-s.com",
                                "created_at":  null,
                                "updated_at":  "2024-01-05T06:56:45.000000Z"
                            },
        "placement":  {
                          "id":  1,
                          "company_id":  "1",
                          "name":  "LinkedIn",
                          "category_id":  "2",
                          "created_at":  "2020-10-26T13:09:46.000000Z",
                          "updated_at":  "2024-01-05T07:05:34.000000Z"
                      },
        "documents":  [

                      ],
        "account_changes":  [
                                {
                                    "id":  4735,
                                    "account_id":  "1666",
                                    "user_id":  "5010",
                                    "value":  "Changed Lead Account Status from Free to Change Password",
                                    "created_at":  "2024-08-30T12:20:33.000000Z",
                                    "updated_at":  "2024-08-30T12:20:33.000000Z",
                                    "user":  null
                                },
                                {
                                    "id":  4736,
                                    "account_id":  "1666",
                                    "user_id":  "5010",
                                    "value":  "Added Approved by manager",
                                    "created_at":  "2024-08-30T12:20:33.000000Z",
                                    "updated_at":  "2024-08-30T12:20:33.000000Z",
                                    "user":  null
                                },
                                {
                                    "id":  4737,
                                    "account_id":  "1666",
                                    "user_id":  "5010",
                                    "value":  "Changed Project Company to Remote Helpers",
                                    "created_at":  "2024-08-30T12:20:33.000000Z",
                                    "updated_at":  "2024-08-30T12:20:33.000000Z",
                                    "user":  null
                                },
                                {
                                    "id":  4738,
                                    "account_id":  "1666",
                                    "user_id":  "5010",
                                    "value":  "Added Created Date 30-08-2024",
                                    "created_at":  "2024-08-30T12:20:33.000000Z",
                                    "updated_at":  "2024-08-30T12:20:33.000000Z",
                                    "user":  null
                                },
                                {
                                    "id":  4817,
                                    "account_id":  "1666",
                                    "user_id":  "5010",
                                    "value":  "Added LG Manager Красножон Дарина Владимировна",
                                    "created_at":  "2024-09-06T11:00:55.000000Z",
                                    "updated_at":  "2024-09-06T11:00:55.000000Z",
                                    "user":  null
                                },
                                {
                                    "id":  4818,
                                    "account_id":  "1666",
                                    "user_id":  "5010",
                                    "value":  "Changed Lead Account Status from Change Password to LG",
                                    "created_at":  "2024-09-06T11:00:55.000000Z",
                                    "updated_at":  "2024-09-06T11:00:55.000000Z",
                                    "user":  null
                                },
                                {
                                    "id":  5859,
                                    "account_id":  "1666",
                                    "user_id":  "5010",
                                    "value":  "Removed LG Manager Красножон Дарина Владимировна",
                                    "created_at":  "2025-01-15T13:09:01.000000Z",
                                    "updated_at":  "2025-01-15T13:09:01.000000Z",
                                    "user":  null
                                },
                                {
                                    "id":  5860,
                                    "account_id":  "1666",
                                    "user_id":  "5010",
                                    "value":  "Changed Account Pass from sashabutloch.2024 to K2T67u8tjE",
                                    "created_at":  "2025-01-15T13:09:01.000000Z",
                                    "updated_at":  "2025-01-15T13:09:01.000000Z",
                                    "user":  null
                                },
                                {
                                    "id":  5861,
                                    "account_id":  "1666",
                                    "user_id":  "5010",
                                    "value":  "Changed Email Password from sashabutloch.2024 to K2T67u8tjE",
                                    "created_at":  "2025-01-15T13:09:01.000000Z",
                                    "updated_at":  "2025-01-15T13:09:01.000000Z",
                                    "user":  null
                                },
                                {
                                    "id":  5862,
                                    "account_id":  "1666",
                                    "user_id":  "5010",
                                    "value":  "Added Connections 9",
                                    "created_at":  "2025-01-15T13:09:01.000000Z",
                                    "updated_at":  "2025-01-15T13:09:01.000000Z",
                                    "user":  null
                                },
                                {
                                    "id":  5863,
                                    "account_id":  "1666",
                                    "user_id":  "5010",
                                    "value":  "Changed Lead Account Status from LG to Free",
                                    "created_at":  "2025-01-15T13:09:01.000000Z",
                                    "updated_at":  "2025-01-15T13:09:01.000000Z",
                                    "user":  null
                                }
                            ],
        "country_histories":  [

                              ],
        "manager_histories":  [
                                  {
                                      "id":  473,
                                      "account_id":  "1666",
                                      "agent_id":  "993",
                                      "project_company_id":  "1",
                                      "start_date":  "2024-09-06T00:00:00.000000Z",
                                      "end_date":  null,
                                      "created_at":  null,
                                      "updated_at":  null,
                                      "agent":  {
                                                    "id":  993,
                                                    "company_id":  "1",
                                                    "user_id":  "8511",
                                                    "status":  "enabled",
                                                    "added_by":  null,
                                                    "last_updated_by":  null,
                                                    "user":  {
                                                                 "id":  8511,
                                                                 "company_id":  "1",
                                                                 "name":  "Красножон Дарина Владимировна",
                                                                 "email":  "azzaz632azzaz@gmail.com",
                                                                 "image":  "8b572ffb48907f21d669f77c5463275a.jpg",
                                                                 "mobile":  "380986615125",
                                                                 "gender":  "female",
                                                                 "locale":  "en",
                                                                 "status":  "active",
                                                                 "login":  "enable",
                                                                 "onesignal_player_id":  null,
                                                                 "created_at":  "2024-05-12T18:21:05+00:00",
                                                                 "updated_at":  "2024-08-19T16:08:36+00:00",
                                                                 "super_admin":  "0",
                                                                 "email_verification_code":  null,
                                                                 "social_token":  null,
                                                                 "email_notifications":  "1",
                                                                 "two_factor_recovery_codes":  null,
                                                                 "two_factor_confirmed":  "0",
                                                                 "two_factor_email_confirmed":  "0",
                                                                 "salutation":  null,
                                                                 "dark_theme":  "0",
                                                                 "rtl":  "0",
                                                                 "two_fa_verify_via":  null,
                                                                 "two_factor_code":  null,
                                                                 "two_factor_expires_at":  null,
                                                                 "admin_approval":  "1",
                                                                 "permission_sync":  "1",
                                                                 "google_calendar_status":  "1",
                                                                 "country_id":  null,
                                                                 "authorize_id":  null,
                                                                 "authorize_payment_id":  null,
                                                                 "card_brand":  null,
                                                                 "card_last_four":  null,
                                                                 "last_login":  null,
                                                                 "image_url":  "https://crm-s.com/user-uploads/avatar/8b572ffb48907f21d669f77c5463275a.jpg",
                                                                 "modules":  [
                                                                                 "clients",
                                                                                 "employees",
                                                                                 "projects",
                                                                                 "attendance",
                                                                                 "tasks",
                                                                                 "estimates",
                                                                                 "invoices",
                                                                                 "payments",
                                                                                 "timelogs",
                                                                                 "tickets",
                                                                                 "events",
                                                                                 "messages",
                                                                                 "notices",
                                                                                 "leaves",
                                                                                 "leads",
                                                                                 "holidays",
                                                                                 "products",
                                                                                 "expenses",
                                                                                 "contracts",
                                                                                 "reports",
                                                                                 "leadAccount",
                                                                                 "leadAgent",
                                                                                 "leadReports",
                                                                                 "leadActivity",
                                                                                 "hr",
                                                                                 "salesAnalytic",
                                                                                 "hrReports",
                                                                                 "hrBonus",
                                                                                 "accounting",
                                                                                 "changeRole",
                                                                                 "translation",
                                                                                 "leadBonus",
                                                                                 "salesBonus",
                                                                                 "financeEmployees",
                                                                                 "employeesVideoEditing",
                                                                                 "employeesCorrespondence",
                                                                                 "hrCorrespondence",
                                                                                 "exchangeRate",
                                                                                 "smmEmployees",
                                                                                 "contentEmployees",
                                                                                 "copywriterEmployees",
                                                                                 "artistEmployees",
                                                                                 "employeeAnalytics",
                                                                                 "employeeDashboard",
                                                                                 "presales",
                                                                                 "communications",
                                                                                 "ticket support",
                                                                                 "library",
                                                                                 "sms_template",
                                                                                 "send_sms"
                                                                             ]
                                                             }
                                                },
                                      "project_company":  {
                                                              "id":  1,
                                                              "company_id":  "1",
                                                              "name":  "Remote Helpers",
                                                              "website":  "https://www.rh-s.com/",
                                                              "short_name":  "rh-s.com",
                                                              "created_at":  null,
                                                              "updated_at":  "2024-01-05T06:56:45.000000Z"
                                                          }
                                  }
                              ],
        "password_histories":  [
                                   {
                                       "id":  1485,
                                       "account_id":  "1666",
                                       "type":  "account",
                                       "old_pass":  "sashabutloch.2024",
                                       "change_date":  "2025-01-15T00:00:00.000000Z",
                                       "created_at":  null,
                                       "updated_at":  null
                                   },
                                   {
                                       "id":  1486,
                                       "account_id":  "1666",
                                       "type":  "email",
                                       "old_pass":  "sashabutloch.2024",
                                       "change_date":  "2025-01-15T00:00:00.000000Z",
                                       "created_at":  null,
                                       "updated_at":  null
                                   }
                               ],
        "premium_histories":  [

                              ]
    },
    {
        "id":  1667,
        "company_id":  "1",
        "project_company_id":  null,
        "name":  "Oleksandr Vitkovskyi",
        "link":  "https://www.linkedin.com/in/vitkovskyi-oleksandr/",
        "connections":  null,
        "premium":  "1",
        "linked_login":  "vitkovskyi.oleksandr1@gmail.com",
        "linked_password":  "OleksandrRemote",
        "email_login":  "vitkovskyi.oleksandr1@gmail.com",
        "email_password":  "OleksandrRemote",
        "passport_link":  null,
        "mobile":  null,
        "comments":  null,
        "buy_date":  null,
        "created_date":  null,
        "banned_date":  null,
        "sold_date":  null,
        "agent_id":  null,
        "status_id":  "3",
        "country_id":  null,
        "source_id":  null,
        "placement_id":  "1",
        "user_id":  "8514",
        "is_approved_manager":  "0",
        "created_at":  "2024-05-13T07:43:15.000000Z",
        "updated_at":  "2024-09-06T14:58:30.000000Z",
        "status":  {
                       "id":  3,
                       "company_id":  "1",
                       "name":  "Free",
                       "created_at":  "2020-09-04T13:03:19.000000Z",
                       "updated_at":  "2020-09-04T13:03:19.000000Z"
                   },
        "country":  null,
        "source":  null,
        "agent":  null,
        "user":  null,
        "project_company":  null,
        "placement":  {
                          "id":  1,
                          "company_id":  "1",
                          "name":  "LinkedIn",
                          "category_id":  "2",
                          "created_at":  "2020-10-26T13:09:46.000000Z",
                          "updated_at":  "2024-01-05T07:05:34.000000Z"
                      },
        "documents":  [

                      ],
        "account_changes":  [

                            ],
        "country_histories":  [

                              ],
        "manager_histories":  [

                              ],
        "password_histories":  [

                               ],
        "premium_histories":  [

                              ]
    },
    {
        "id":  1668,
        "company_id":  "1",
        "project_company_id":  null,
        "name":  "Maksym Severyn",
        "link":  "https://www.linkedin.com/in/maksym-severyn-494147309/",
        "connections":  null,
        "premium":  "1",
        "linked_login":  "maksym.severynrm@gmail.com",
        "linked_password":  "maxremoteemp2024",
        "email_login":  "maksym.severynrm@gmail.com",
        "email_password":  "maxremoteemp2024",
        "passport_link":  null,
        "mobile":  null,
        "comments":  null,
        "buy_date":  null,
        "created_date":  null,
        "banned_date":  null,
        "sold_date":  null,
        "agent_id":  null,
        "status_id":  "3",
        "country_id":  null,
        "source_id":  null,
        "placement_id":  "1",
        "user_id":  "8517",
        "is_approved_manager":  "0",
        "created_at":  "2024-05-13T07:44:38.000000Z",
        "updated_at":  "2024-05-13T07:44:38.000000Z",
        "status":  {
                       "id":  3,
                       "company_id":  "1",
                       "name":  "Free",
                       "created_at":  "2020-09-04T13:03:19.000000Z",
                       "updated_at":  "2020-09-04T13:03:19.000000Z"
                   },
        "country":  null,
        "source":  null,
        "agent":  null,
        "user":  null,
        "project_company":  null,
        "placement":  {
                          "id":  1,
                          "company_id":  "1",
                          "name":  "LinkedIn",
                          "category_id":  "2",
                          "created_at":  "2020-10-26T13:09:46.000000Z",
                          "updated_at":  "2024-01-05T07:05:34.000000Z"
                      },
        "documents":  [

                      ],
        "account_changes":  [

                            ],
        "country_histories":  [

                              ],
        "manager_histories":  [

                              ],
        "password_histories":  [

                               ],
        "premium_histories":  [

                              ]
    }
]
